special_attentions/Golden_attention.py
special_attentions/LocalGlobalAttention.py
special_attentions/MergeAttention.py
special_attentions/SildingTileAttention.py
special_attentions/SmartAttention.py
special_attentions/SparseGen_Plus.py
special_attentions/__init__.py
special_attentions/block_mask_attn.py
special_attentions/combined_attn.py
special_attentions/partern_attention.py
special_attentions/setup.py
special_attentions/TrainRelated/__init__.py
special_attentions/TrainRelated/blocksparseattn.py
special_attentions/utils/__init__.py
special_attentions/utils/attn_pooling_kernel.py
special_attentions/utils/block_sparse_attn_kernel.py
special_attentions/utils/gilbert3d.py
special_attentions/utils/mask_related.py
special_attentions/utils/merge_unmerge.py
special_attentions/utils/tools.py
special_attentions_pack-0.3.0.dist-info/METADATA
special_attentions_pack-0.3.0.dist-info/WHEEL
special_attentions_pack-0.3.0.dist-info/top_level.txt
special_attentions_pack-0.3.0.dist-info/RECORD
