Metadata-Version: 2.4
Name: special-attentions-pack
Version: 0.3.0
Summary: A collection of sparse attention mechanisms
Home-page: https://github.com/yourname/special_attentions
Author: Your Name
Author-email: you@example.com
License: MIT
Classifier: Programming Language :: Python :: 3
Classifier: License :: OSI Approved :: MIT License
Classifier: Operating System :: OS Independent
Requires-Python: >=3.7
Provides-Extra: dev
Requires-Dist: pytest; extra == "dev"
Requires-Dist: flake8; extra == "dev"
Dynamic: author
Dynamic: author-email
Dynamic: classifier
Dynamic: description
Dynamic: description-content-type
Dynamic: home-page
Dynamic: license
Dynamic: provides-extra
Dynamic: requires-python
Dynamic: summary
